setup.py
funniest/__init__.py
funniest/text.py
ibbifunniest.egg-info/PKG-INFO
ibbifunniest.egg-info/SOURCES.txt
ibbifunniest.egg-info/dependency_links.txt
ibbifunniest.egg-info/not-zip-safe
ibbifunniest.egg-info/top_level.txt