Metadata-Version: 1.0
Name: ibbifunniest
Version: 0.1.1
Summary: The funniest joke in the world
Home-page: UNKNOWN
Author: Ihor Bilous
Author-email: ihorkobilous@gmail.com
License: MIT
Platform: UNKNOWN
